Metadata-Version: 2.1
Name: ddrage
Version: 1.8.1
Summary: Simulator for ddRADseq (double digest restriction site associated DNA sequencing) datasets. Generates reads (FASTQ format) that can be analyzed and validated using a ground truth file (YAML).
Author-email: Henning Timm <henning.timm@uni-due.de>
License: The MIT License (MIT)
Project-URL: Homepage, https://ddrage.readthedocs.io/en/latest/
Project-URL: Documentation, https://ddrage.readthedocs.io/en/latest/
Project-URL: Repository, https://bitbucket.org/genomeinformatics/rage
Project-URL: Bug Tracker, https://bitbucket.org/genomeinformatics/rage/issues
Project-URL: Changelog, https://ddrage.readthedocs.io/en/latest/changelog/
Classifier: Development Status :: 5 - Production/Stable
Classifier: Intended Audience :: Developers
Classifier: Intended Audience :: Science/Research
Classifier: License :: OSI Approved :: MIT License
Classifier: Natural Language :: English
Classifier: Programming Language :: Python :: 3
Classifier: Programming Language :: Python :: 3.8
Classifier: Programming Language :: Python :: 3.9
Classifier: Programming Language :: Python :: 3.10
Classifier: Programming Language :: Python :: 3.11
Classifier: Programming Language :: Python :: 3.12
Classifier: Topic :: Scientific/Engineering :: Bio-Informatics
Classifier: Topic :: Scientific/Engineering :: Medical Science Apps.
License-File: LICENSE.rst
Requires-Dist: numpy
Requires-Dist: numba
Requires-Dist: matplotlib
Requires-Dist: seaborn
Requires-Dist: scipy >=1.4.1
Requires-Dist: pyyaml
Requires-Dist: dinopy
Provides-Extra: bbd-visualization
Requires-Dist: bokeh >=3.1.1 ; extra == 'bbd-visualization'
Provides-Extra: documentation
Requires-Dist: sphinx >=1.5.0 ; extra == 'documentation'
